cvdast/CloudvectorDAST.py
cvdast/__init__.py
cvdast/test.py
cvdast/trafficgen.yaml
cvdast/assets/style.css
cvdast/fuzzdb/README.md
cvdast/fuzzdb/_copyright.txt
cvdast/fuzzdb/fuzzdb-icon.png
cvdast/fuzzdb/fuzzdb.png
cvdast/fuzzdb/attack/README.md
cvdast/fuzzdb/attack/authentication/README.md
cvdast/fuzzdb/attack/authentication/php_magic_hashes.fuzz.txt
cvdast/fuzzdb/attack/business-logic/CommonDebugParamNames.txt
cvdast/fuzzdb/attack/business-logic/CommonMethodNames.txt
cvdast/fuzzdb/attack/business-logic/DebugParams.Json.fuzz.txt
cvdast/fuzzdb/attack/control-chars/HexValsAllBytes.txt
cvdast/fuzzdb/attack/control-chars/NullByteRepresentations.txt
cvdast/fuzzdb/attack/control-chars/imessage.txt
cvdast/fuzzdb/attack/control-chars/terminal-escape-codes.txt
cvdast/fuzzdb/attack/control-chars/true.txt
cvdast/fuzzdb/attack/disclosure-directory/directory-indexing-generic.txt
cvdast/fuzzdb/attack/disclosure-localpaths/unix/common-unix-httpd-log-locations.txt
cvdast/fuzzdb/attack/disclosure-source/README.md
cvdast/fuzzdb/attack/disclosure-source/source-disc-cmd-exec-traversal.txt
cvdast/fuzzdb/attack/disclosure-source/source-disclosure-generic.txt
cvdast/fuzzdb/attack/disclosure-source/source-disclosure-microsoft.txt
cvdast/fuzzdb/attack/file-upload/README.md
cvdast/fuzzdb/attack/file-upload/alt-extensions-asp.txt
cvdast/fuzzdb/attack/file-upload/alt-extensions-coldfusion.txt
cvdast/fuzzdb/attack/file-upload/alt-extensions-jsp.txt
cvdast/fuzzdb/attack/file-upload/alt-extensions-perl.txt
cvdast/fuzzdb/attack/file-upload/alt-extensions-php.txt
cvdast/fuzzdb/attack/file-upload/file-ul-filter-bypass-commonly-writable-directories.txt
cvdast/fuzzdb/attack/file-upload/file-ul-filter-bypass-microsoft-asp-filetype-bf.txt
cvdast/fuzzdb/attack/file-upload/file-ul-filter-bypass-microsoft-asp.txt
cvdast/fuzzdb/attack/file-upload/file-ul-filter-bypass-ms-php.txt
cvdast/fuzzdb/attack/file-upload/file-ul-filter-bypass-x-platform-generic.txt
cvdast-1.48.18.dist-info/METADATA
cvdast-1.48.18.dist-info/WHEEL
cvdast-1.48.18.dist-info/entry_points.txt
cvdast-1.48.18.dist-info/top_level.txt
cvdast-1.48.18.dist-info/RECORD
