Metadata-Version: 2.1
Name: cvdast
Version: 1.48.18
Summary: To regenerate pytest fixtures and test methods dynamically from OpenAPI spec and Cloudvector APIShark events
Author: Bala Kumaran
Author-email: balak@cloudvector.com
License: UNKNOWN
Platform: UNKNOWN
Requires-Python: >=3.7,<4.0
Requires-Dist: PyYAML (==5.3.1)
Requires-Dist: autopep8 (==1.5.4)
Requires-Dist: curlify (==2.2.1)
Requires-Dist: cvapianalyser (==1.43.6)
Requires-Dist: dictor (==0.1.7)
Requires-Dist: jinja2 (==3.0.3)
Requires-Dist: nested-lookup (==0.2.21)
Requires-Dist: openapispecdiff (==1.43.7)
Requires-Dist: pytest-cases (==1.16.0)
Requires-Dist: pytest-html (==3.1.1)
Requires-Dist: pytest-metadata (==1.11.0)
Requires-Dist: pytest-json (==0.4.0)
Requires-Dist: pytest-lazy-fixture (==0.6.3)
Requires-Dist: pytest-rerunfailures (==9.0)
Requires-Dist: pytest-testrail (==2.9.0)
Requires-Dist: pytest-timeout (==1.4.2)
Requires-Dist: pytest (==5.4.3)
Requires-Dist: requests
Requires-Dist: tqdm (==4.46.1)
Requires-Dist: MarkupSafe (==2.0.1)
Requires-Dist: validators (==0.18.0)
